MANIFEST.in
README.rst
setup.cfg
setup.py
docs/changes.rst
docs/contributors.rst
src/demopy/__init__.py
src/demopy.egg-info/PKG-INFO
src/demopy.egg-info/SOURCES.txt
src/demopy.egg-info/dependency_links.txt
src/demopy.egg-info/not-zip-safe
src/demopy.egg-info/requires.txt
src/demopy.egg-info/top_level.txt