Metadata-Version: 1.1
Name: demopy
Version: 1.0.0.dev0
Summary: Une démo de packaging
Home-page: http://pypi.python.org/pypi/demopy
Author: Gilles lenfant
Author-email: gilles.lenfant@alterway.fr
License: GPLv3
Platform: UNKNOWN
Classifier: Programming Language :: Python
Classifier: License :: OSI Approved :: GNU General Public License v3 (GPLv3)
